jinjacli.py
jinjacli-0.1.0.dist-info/METADATA
jinjacli-0.1.0.dist-info/WHEEL
jinjacli-0.1.0.dist-info/entry_points.txt
jinjacli-0.1.0.dist-info/top_level.txt
jinjacli-0.1.0.dist-info/RECORD
